Workbook

Sheet 00_口径说明
A1: 项目 | B1: 说明
A2: 数据截点 | B2: 2026-10-29；D两份8条评分已收且相同。未完成受控人工写作任务。
A3: 用途 | B3: 本簿区分日志实测、参考费用、评分校准和假设情景。不能把情景工资/时间写成企业实测。
A4: 身份 | B4: 金金有味队：李牧轩、刘铠侨、李泽锴、黄玺诺；天津大学分赛场。
A5: 费用 | B5: 每次(input_tokens×input_rate+output_tokens×output_rate)/1000000；本轮缓存命中0。
A6: 评价 | B6: A校准后与D均3/8通过；首次A与D门槛一致3/8。逐维口径仍有分歧，不作正式信度验证或模型排名。
A7: 来源 | B7: 01日志来自C交付经核验数据；评分来自v1.5。参考链接见文稿。
A8: 公式 | B8: Excel公式可重算；绿色或蓝色值为已记录数据，情景假设另表。空白实付、D评分均不得填0。
A9: 保密流程 | B9: D自述未看A评分、答案或映射，队长确认未看CAL04/07改分讨论；含内部修订，最早未修订版未收。无访问日志审计。

Sheet 01_逐次费用
A1: 匿名ID | B1: 题号 | C1: 模型 | D1: 流程 | E1: 输入Token | F1: 输出Token | G1: 输入单价_元每百万 | H1: 输出单价_元每百万 | I1: 复算费用_元 | J1: 原记录参考费_元 | K1: 差额 | L1: 缓存命中Token | M1: 调用时间北京时间 | N1: 实际支付_待账单 | O1: 来源状态
A2: CAL-01 | B2: P-A07 | C2: 千问 | D2: boundary | E2: 1339 | F2: 276 | G2: 0.2 | H2: 0.8 | I2: =(E2*G2+F2*H2)/1000000 -> 0.0004886 | J2: 0.0004886 | K2: =I2-J2 -> 0 | L2: 0 | M2: 2026-10-24T00:08:04.880+08:00 | O2: 日志用量；单价复算，非实付
A3: CAL-02 | B3: P-A08 | C3: DeepSeek | D3: boundary | E3: 3737 | F3: 229 | G3: 1 | H3: 4 | I3: =(E3*G3+F3*H3)/1000000 -> 0.004653 | J3: 0.004653 | K3: =I3-J3 -> 0 | L3: 0 | M3: 2026-10-24T00:08:09.272+08:00 | O3: 日志用量；单价复算，非实付
A4: CAL-03 | B4: P-A07 | C4: DeepSeek | D4: direct | E4: 1104 | F4: 123 | G4: 1 | H4: 4 | I4: =(E4*G4+F4*H4)/1000000 -> 0.001596 | J4: 0.001596 | K4: =I4-J4 -> 0 | L4: 0 | M4: 2026-10-24T00:08:12.227+08:00 | O4: 日志用量；单价复算，非实付
A5: CAL-04 | B5: P-A08 | C5: 千问 | D5: direct | E5: 4530 | F5: 192 | G5: 0.2 | H5: 0.8 | I5: =(E5*G5+F5*H5)/1000000 -> 0.0010596 | J5: 0.0010596 | K5: =I5-J5 -> 0 | L5: 0 | M5: 2026-10-24T00:08:13.997+08:00 | O5: 日志用量；单价复算，非实付
A6: CAL-05 | B6: P-A08 | C6: 千问 | D6: boundary | E6: 4577 | F6: 296 | G6: 0.2 | H6: 0.8 | I6: =(E6*G6+F6*H6)/1000000 -> 0.0011522 | J6: 0.0011522 | K6: =I6-J6 -> 0 | L6: 0 | M6: 2026-10-24T00:08:18.342+08:00 | O6: 日志用量；单价复算，非实付
A7: CAL-06 | B7: P-A07 | C7: DeepSeek | D7: boundary | E7: 1152 | F7: 207 | G7: 1 | H7: 4 | I7: =(E7*G7+F7*H7)/1000000 -> 0.00198 | J7: 0.00198 | K7: =I7-J7 -> 0 | L7: 0 | M7: 2026-10-24T00:08:25.046+08:00 | O7: 日志用量；单价复算，非实付
A8: CAL-07 | B8: P-A07 | C8: 千问 | D8: direct | E8: 1292 | F8: 145 | G8: 0.2 | H8: 0.8 | I8: =(E8*G8+F8*H8)/1000000 -> 0.0003744 | J8: 0.0003744 | K8: =I8-J8 -> 0 | L8: 0 | M8: 2026-10-24T00:08:27.584+08:00 | O8: 日志用量；单价复算，非实付
A9: CAL-08 | B9: P-A08 | C9: DeepSeek | D9: direct | E9: 3689 | F9: 150 | G9: 1 | H9: 4 | I9: =(E9*G9+F9*H9)/1000000 -> 0.004289 | J9: 0.004289 | K9: =I9-J9 -> 0 | L9: 0 | M9: 2026-10-24T00:08:31.304+08:00 | O9: 日志用量；单价复算，非实付
A10: 合计 | E10: =SUM(E2:E9) -> 21420 | F10: =SUM(F2:F9) -> 1618 | I10: =SUM(I2:I9) -> 0.0155928 | J10: =SUM(J2:J9) -> 0.0155928 | K10: =SUM(K2:K9) -> 0 | L10: =SUM(L2:L9) -> 0 | O10: 8次/2题

Sheet 02_四条件汇总
A1: 模型 | B1: 流程 | C1: 次数 | D1: 输入Token | E1: 输出Token | F1: 参考费用合计 | G1: 平均每次费用 | H1: 备注
A2: DeepSeek | B2: direct | C2: =COUNTIFS('01_逐次费用'!$C$2:$C$9,A2,'01_逐次费用'!$D$2:$D$9,B2) -> 2 | D2: =SUMIFS('01_逐次费用'!$E$2:$E$9,'01_逐次费用'!$C$2:$C$9,A2,'01_逐次费用'!$D$2:$D$9,B2) -> 4793 | E2: =SUMIFS('01_逐次费用'!$F$2:$F$9,'01_逐次费用'!$C$2:$C$9,A2,'01_逐次费用'!$D$2:$D$9,B2) -> 273 | F2: =SUMIFS('01_逐次费用'!$I$2:$I$9,'01_逐次费用'!$C$2:$C$9,A2,'01_逐次费用'!$D$2:$D$9,B2) -> 0.005885 | G2: =F2/C2 -> 0.0029425 | H2: 两题各一次，不做质量排名
A3: DeepSeek | B3: boundary | C3: =COUNTIFS('01_逐次费用'!$C$2:$C$9,A3,'01_逐次费用'!$D$2:$D$9,B3) -> 2 | D3: =SUMIFS('01_逐次费用'!$E$2:$E$9,'01_逐次费用'!$C$2:$C$9,A3,'01_逐次费用'!$D$2:$D$9,B3) -> 4889 | E3: =SUMIFS('01_逐次费用'!$F$2:$F$9,'01_逐次费用'!$C$2:$C$9,A3,'01_逐次费用'!$D$2:$D$9,B3) -> 436 | F3: =SUMIFS('01_逐次费用'!$I$2:$I$9,'01_逐次费用'!$C$2:$C$9,A3,'01_逐次费用'!$D$2:$D$9,B3) -> 0.006633 | G3: =F3/C3 -> 0.0033165 | H3: 两题各一次，不做质量排名
A4: 千问 | B4: direct | C4: =COUNTIFS('01_逐次费用'!$C$2:$C$9,A4,'01_逐次费用'!$D$2:$D$9,B4) -> 2 | D4: =SUMIFS('01_逐次费用'!$E$2:$E$9,'01_逐次费用'!$C$2:$C$9,A4,'01_逐次费用'!$D$2:$D$9,B4) -> 5822 | E4: =SUMIFS('01_逐次费用'!$F$2:$F$9,'01_逐次费用'!$C$2:$C$9,A4,'01_逐次费用'!$D$2:$D$9,B4) -> 337 | F4: =SUMIFS('01_逐次费用'!$I$2:$I$9,'01_逐次费用'!$C$2:$C$9,A4,'01_逐次费用'!$D$2:$D$9,B4) -> 0.001434 | G4: =F4/C4 -> 0.000717 | H4: 两题各一次，不做质量排名
A5: 千问 | B5: boundary | C5: =COUNTIFS('01_逐次费用'!$C$2:$C$9,A5,'01_逐次费用'!$D$2:$D$9,B5) -> 2 | D5: =SUMIFS('01_逐次费用'!$E$2:$E$9,'01_逐次费用'!$C$2:$C$9,A5,'01_逐次费用'!$D$2:$D$9,B5) -> 5916 | E5: =SUMIFS('01_逐次费用'!$F$2:$F$9,'01_逐次费用'!$C$2:$C$9,A5,'01_逐次费用'!$D$2:$D$9,B5) -> 572 | F5: =SUMIFS('01_逐次费用'!$I$2:$I$9,'01_逐次费用'!$C$2:$C$9,A5,'01_逐次费用'!$D$2:$D$9,B5) -> 0.0016408 | G5: =F5/C5 -> 0.0008204 | H5: 两题各一次，不做质量排名

Sheet 03_A校准与D门槛
A1: 匿名ID | B1: 题号 | C1: F | D1: E | E1: C | F1: B | G1: 关键错误 | H1: 标准U | I1: 当前门槛 | J1: 评分来源 | K1: D回传门槛 | L1: 当前共同门槛_非细项裁定
A2: CAL-01 | B2: P-A07 | C2: 2 | D2: 2 | E2: 2 | F2: 2 | G2: 否 | H2: 否 | I2: 通过 | J2: 沿用A复核版 | K2: 通过 | L2: =IF(I2=K2,K2,"分歧") -> 通过
A3: CAL-02 | B3: P-A08 | C3: 2 | D3: 2 | E3: 1 | F3: 2 | G3: 否 | H3: 否 | I3: 未通过 | J3: 沿用A复核版 | K3: 未通过 | L3: =IF(I3=K3,K3,"分歧") -> 未通过
A4: CAL-03 | B4: P-A07 | C4: 2 | D4: 2 | E4: 2 | F4: 2 | G4: 否 | H4: 否 | I4: 通过 | J4: 沿用A复核版 | K4: 通过 | L4: =IF(I4=K4,K4,"分歧") -> 通过
A5: CAL-04 | B5: P-A08 | C5: 0 | D5: 0 | E5: 1 | F5: 0 | G5: 是 | H5: 否 | I5: 未通过 | J5: 助手辅助裁定 | K5: 未通过 | L5: =IF(I5=K5,K5,"分歧") -> 未通过
A6: CAL-05 | B6: P-A08 | C6: 2 | D6: 2 | E6: 1 | F6: 2 | G6: 否 | H6: 否 | I6: 未通过 | J6: 沿用A复核版 | K6: 未通过 | L6: =IF(I6=K6,K6,"分歧") -> 未通过
A7: CAL-06 | B7: P-A07 | C7: 2 | D7: 2 | E7: 2 | F7: 2 | G7: 否 | H7: 否 | I7: 通过 | J7: 沿用A复核版 | K7: 通过 | L7: =IF(I7=K7,K7,"分歧") -> 通过
A8: CAL-07 | B8: P-A07 | C8: 0 | D8: 0 | E8: 1 | F8: 0 | G8: 是 | H8: 否 | I8: 未通过 | J8: 助手辅助裁定 | K8: 未通过 | L8: =IF(I8=K8,K8,"分歧") -> 未通过
A9: CAL-08 | B9: P-A08 | C9: 2 | D9: 2 | E9: 1 | F9: 2 | G9: 否 | H9: 否 | I9: 未通过 | J9: 沿用A复核版 | K9: 未通过 | L9: =IF(I9=K9,K9,"分歧") -> 未通过

Sheet 04_价格折扣情景
A1: 假设API成本占比 | B1: 假设API降价比例 | C1: 总成本下降比例 | D1: 其他条件
A2: 0 | B2: 0.5 | C2: =A2*B2 -> 0 | D2: 质量/用量/人工/合格数固定；非实测占比
A3: 0.01 | B3: 0.5 | C3: =A3*B3 -> 0.005 | D3: 质量/用量/人工/合格数固定；非实测占比
A4: 0.05 | B4: 0.5 | C4: =A4*B4 -> 0.025 | D4: 质量/用量/人工/合格数固定；非实测占比
A5: 0.1 | B5: 0.5 | C5: =A5*B5 -> 0.05 | D5: 质量/用量/人工/合格数固定；非实测占比
A6: 0.2 | B6: 0.5 | C6: =A6*B6 -> 0.1 | D6: 质量/用量/人工/合格数固定；非实测占比
A7: 0.3 | B7: 0.5 | C7: =A7*B7 -> 0.15 | D7: 质量/用量/人工/合格数固定；非实测占比
A8: 0.5 | B8: 0.5 | C8: =A8*B8 -> 0.25 | D8: 质量/用量/人工/合格数固定；非实测占比
A9: 0.75 | B9: 0.5 | C9: =A9*B9 -> 0.375 | D9: 质量/用量/人工/合格数固定；非实测占比
A10: 1 | B10: 0.5 | C10: =A10*B10 -> 0.5 | D10: 质量/用量/人工/合格数固定；非实测占比

Sheet 05_人工时间情景
A1: 假设小时价值 | B1: 假设分钟每条 | C1: 平均API费锚点 | D1: 人工费用 | E1: 部分总额 | F1: API降价50%后部分总额 | G1: 总额降幅 | H1: 说明
A2: 60 | B2: 0 | C2: ='01_逐次费用'!I10/8 -> 0.0019491 | D2: =A2*B2/60 -> 0 | E2: =C2+D2 -> 0.0019491 | F2: =C2*0.5+D2 -> 0.00097455 | G2: =(E2-F2)/E2 -> 0.5 | H2: 情景；未计准备、部署及质量差异
A3: 60 | B3: 1 | C3: ='01_逐次费用'!I10/8 -> 0.0019491 | D3: =A3*B3/60 -> 1 | E3: =C3+D3 -> 1.0019491 | F3: =C3*0.5+D3 -> 1.0009746 | G3: =(E3-F3)/E3 -> 0.0009726542 | H3: 情景；未计准备、部署及质量差异
A4: 60 | B4: 3 | C4: ='01_逐次费用'!I10/8 -> 0.0019491 | D4: =A4*B4/60 -> 3 | E4: =C4+D4 -> 3.0019491 | F4: =C4*0.5+D4 -> 3.0009746 | G4: =(E4-F4)/E4 -> 0.00032463908 | H4: 情景；未计准备、部署及质量差异
A5: 60 | B5: 5 | C5: ='01_逐次费用'!I10/8 -> 0.0019491 | D5: =A5*B5/60 -> 5 | E5: =C5+D5 -> 5.0019491 | F5: =C5*0.5+D5 -> 5.0009745 | G5: =(E5-F5)/E5 -> 0.00019483405 | H5: 情景；未计准备、部署及质量差异
A6: 60 | B6: 10 | C6: ='01_逐次费用'!I10/8 -> 0.0019491 | D6: =A6*B6/60 -> 10 | E6: =C6+D6 -> 10.001949 | F6: =C6*0.5+D6 -> 10.000975 | G6: =(E6-F6)/E6 -> 9.7436009e-05 | H6: 情景；未计准备、部署及质量差异
A7: 120 | B7: 0 | C7: ='01_逐次费用'!I10/8 -> 0.0019491 | D7: =A7*B7/60 -> 0 | E7: =C7+D7 -> 0.0019491 | F7: =C7*0.5+D7 -> 0.00097455 | G7: =(E7-F7)/E7 -> 0.5 | H7: 情景；未计准备、部署及质量差异
A8: 120 | B8: 1 | C8: ='01_逐次费用'!I10/8 -> 0.0019491 | D8: =A8*B8/60 -> 2 | E8: =C8+D8 -> 2.0019491 | F8: =C8*0.5+D8 -> 2.0009746 | G8: =(E8-F8)/E8 -> 0.00048680059 | H8: 情景；未计准备、部署及质量差异
A9: 120 | B9: 3 | C9: ='01_逐次费用'!I10/8 -> 0.0019491 | D9: =A9*B9/60 -> 6 | E9: =C9+D9 -> 6.0019491 | F9: =C9*0.5+D9 -> 6.0009745 | G9: =(E9-F9)/E9 -> 0.00016237225 | H9: 情景；未计准备、部署及质量差异
A10: 120 | B10: 5 | C10: ='01_逐次费用'!I10/8 -> 0.0019491 | D10: =A10*B10/60 -> 10 | E10: =C10+D10 -> 10.001949 | F10: =C10*0.5+D10 -> 10.000975 | G10: =(E10-F10)/E10 -> 9.7436009e-05 | H10: 情景；未计准备、部署及质量差异
A11: 120 | B11: 10 | C11: ='01_逐次费用'!I10/8 -> 0.0019491 | D11: =A11*B11/60 -> 20 | E11: =C11+D11 -> 20.001949 | F11: =C11*0.5+D11 -> 20.000975 | G11: =(E11-F11)/E11 -> 4.8722752e-05 | H11: 情景；未计准备、部署及质量差异
A12: 240 | B12: 0 | C12: ='01_逐次费用'!I10/8 -> 0.0019491 | D12: =A12*B12/60 -> 0 | E12: =C12+D12 -> 0.0019491 | F12: =C12*0.5+D12 -> 0.00097455 | G12: =(E12-F12)/E12 -> 0.5 | H12: 情景；未计准备、部署及质量差异
A13: 240 | B13: 1 | C13: ='01_逐次费用'!I10/8 -> 0.0019491 | D13: =A13*B13/60 -> 4 | E13: =C13+D13 -> 4.0019491 | F13: =C13*0.5+D13 -> 4.0009745 | G13: =(E13-F13)/E13 -> 0.00024351884 | H13: 情景；未计准备、部署及质量差异
A14: 240 | B14: 3 | C14: ='01_逐次费用'!I10/8 -> 0.0019491 | D14: =A14*B14/60 -> 12 | E14: =C14+D14 -> 12.001949 | F14: =C14*0.5+D14 -> 12.000975 | G14: =(E14-F14)/E14 -> 8.1199311e-05 | H14: 情景；未计准备、部署及质量差异
A15: 240 | B15: 5 | C15: ='01_逐次费用'!I10/8 -> 0.0019491 | D15: =A15*B15/60 -> 20 | E15: =C15+D15 -> 20.001949 | F15: =C15*0.5+D15 -> 20.000975 | G15: =(E15-F15)/E15 -> 4.8722752e-05 | H15: 情景；未计准备、部署及质量差异
A16: 240 | B16: 10 | C16: ='01_逐次费用'!I10/8 -> 0.0019491 | D16: =A16*B16/60 -> 40 | E16: =C16+D16 -> 40.001949 | F16: =C16*0.5+D16 -> 40.000975 | G16: =(E16-F16)/E16 -> 2.4362563e-05 | H16: 情景；未计准备、部署及质量差异

Sheet 06_炊具均值复算
A1: 期间 | B1: 收入元 | C1: 销量台或套 | D1: 类别平均收入 | E1: 平均收入同比 | F1: 证据
A2: 2024 | B2: 6.836158e+09 | C2: 85724597 | D2: =B2/C2 -> 79.745584 | F2: 苏泊尔年报原13—14页
A3: 2025 | B3: 6.965678e+09 | C3: 92664612 | D3: =B3/C3 -> 75.170854 | E3: =D3/D2-1 -> -0.057366565 | F3: 推导值，不是同款价格

Sheet 07_文献与页码
A1: 编号 | B1: 文献 | C1: 类型 | D1: 样本 | E1: 指标 | F1: 结论边界 | G1: 正文页码 | H1: PDF对应 | I1: 链接
A2: 3 | B2: Chen等，2025-08-05 | C2: 工作稿，非期刊 | D2: 4680公司；7818963公司—交易日 | E2: 报价价差；提问/评论及回复分类 | F2: 质量关联不能当AI生成准确率或因果 | G2: 9—10；18—21；表6B 45 | H2: 正文+1 | I2: https://papers.ssrn.com/sol3/papers.cfm?abstract_id=4281898
A3: 4 | B3: 徐寿福、郑迎飞、罗雨杰，2022 | C3: 财经研究48(10):153—168 | D3: 92155公司—季度 | E3: 互动频次/文本；残差波动 | F3: 互动与风险关系不证明AI造成风险 | G3: 156—159；162 | H3: 印刷页-152 | I3: https://qks.shufe.edu.cn/j/PDFFull/17794c14-b22d-4e71-b91b-053fc480a45a.pdf
A4: 5 | B4: 樊犇、吴燕博、刘恒源，2026 | C4: 审计与经济研究41(4):94—104 | D4: 25996公司—年度 | E4: LLM识别监督；真实盈余管理 | F4: LLM文本测量不等于生成回复可靠 | G4: 97—101 | H4: 印刷页-93 | I4: https://xbbjb.nau.edu.cn/sjyjjyj/article/abstract/20260204010

Sheet 08_提交检查
A1: 事项 | B1: 当前状态 | C1: 操作 | D1: 依据
A2: 赛场 | B2: 已确认 | C2: 仅天津大学分赛场 | D2: 用户10/28确认；手册16—18页
A3: 截止 | B3: 已确认 | C3: 2026-10-29 22:00前，内部18:00 | D3: 用户确认天大通知有效
A4: 邮箱 | B4: 已确认 | C4: tjucomers2026@163.com；发送Word和PDF | D4: 用户确认；助手未代发
A5: 署名 | B5: 已确认 | C5: 金金有味队；李牧轩 刘铠侨 李泽锴 黄玺诺 | D5: 用户提供
A6: 电话邮箱 | B6: 不在公开稿中收集 | C6: 队长本地补入正式提交文件名 | D6: 手册命名格式及本地通知
A7: 全文字数 | B7: 已检查：含表格可见字符17542，低于30000 | C7: 全文含附录、参考文献、文本框、脚注尾注均控制30000以内 | D7: 手册18页
A8: 字体 | B8: Word已设；PDF环境替代 | C8: 有宋体/Times New Roman电脑本地打开Word重新导出PDF | D8: 当前环境缺规定字体
A9: D评分 | B9: 8条已收，两份一致 | C9: 首次A与D一致37.5%；校准后同3/8通过，保留细项分歧 | D9: D回传两份原件；D自述独立且含内部修订
A10: C账单 | B10: 未回收 | C10: 实付缺失则保留参考价标签，不填0 | D10: 费用来源
A11: 新增样本 | B11: 待核验 | C11: 合格来源补入收集状态；无新调用不能增加实验数 | D11: 时间截止原则
A12: 附件一致 | B12: 待最终本地导出 | C12: 打开Word/PDF逐页检查图表、字体、目录及页码 | D12: 提交前
A13: 发送回执 | B13: 未发送 | C13: 核对邮箱/文件名/附件可读，保存发送及回执 | D13: 队长执行

Sheet 09_评分版本比较
A1: 匿名ID | B1: 题号 | C1: A首次通过1否0 | D1: A复核通过 | E1: A辅助通过 | F1: D提交通过 | G1: 首次A与D一致 | H1: 校准后与D一致 | I1: 版本备注
A2: CAL-01 | B2: P-A07 | C2: 1 | D2: 1 | E2: 1 | F2: 1 | G2: 1 | H2: 1 | I2: D自述未看A评分/参考答案/映射；含内部修订
A3: CAL-02 | B3: P-A08 | C3: 1 | D3: 0 | E3: 0 | F3: 0 | G3: 0 | H3: 1 | I3: D自述未看A评分/参考答案/映射；含内部修订
A4: CAL-03 | B4: P-A07 | C4: 1 | D4: 1 | E4: 1 | F4: 1 | G4: 1 | H4: 1 | I4: D自述未看A评分/参考答案/映射；含内部修订
A5: CAL-04 | B5: P-A08 | C5: 1 | D5: 0 | E5: 0 | F5: 0 | G5: 0 | H5: 1 | I5: D自述未看A评分/参考答案/映射；含内部修订
A6: CAL-05 | B6: P-A08 | C6: 1 | D6: 0 | E6: 0 | F6: 0 | G6: 0 | H6: 1 | I6: D自述未看A评分/参考答案/映射；含内部修订
A7: CAL-06 | B7: P-A07 | C7: 1 | D7: 1 | E7: 1 | F7: 1 | G7: 1 | H7: 1 | I7: D自述未看A评分/参考答案/映射；含内部修订
A8: CAL-07 | B8: P-A07 | C8: 1 | D8: 0 | E8: 0 | F8: 0 | G8: 0 | H8: 1 | I8: D自述未看A评分/参考答案/映射；含内部修订
A9: CAL-08 | B9: P-A08 | C9: 1 | D9: 0 | E9: 0 | F9: 0 | G9: 0 | H9: 1 | I9: D自述未看A评分/参考答案/映射；含内部修订

Sheet 10_细项分歧
A1: 匿名ID | B1: 字段 | C1: A首次 | D1: A复核 | E1: A辅助 | F1: D提交 | G1: 处理状态
A2: CAL-04 | B2: F | C2: 2 | D2: 2 | E2: 0 | F2: 2 | G2: 保留双方原值；未取得逐维共同裁定
A3: CAL-04 | B3: E | C3: 2 | D3: 2 | E3: 0 | F3: 2 | G3: 保留双方原值；未取得逐维共同裁定
A4: CAL-04 | B4: C | C4: 2 | D4: 1 | E4: 1 | F4: 0 | G4: 保留双方原值；未取得逐维共同裁定
A5: CAL-04 | B5: B | C5: 2 | D5: 2 | E5: 0 | F5: 1 | G5: 保留双方原值；未取得逐维共同裁定
A6: CAL-05 | B6: C | C6: 2 | D6: 1 | E6: 1 | F6: 0 | G6: 保留双方原值；未取得逐维共同裁定
A7: CAL-05 | B7: 过度拒答 | C7: 否 | D7: 否 | E7: 否 | F7: 是 | G7: 保留双方原值；未取得逐维共同裁定
A8: CAL-05 | B8: 覆盖核心数 | C8: 2 | D8: 2 | E8: 2 | F8: 1 | G8: 保留双方原值；未取得逐维共同裁定
A9: CAL-07 | B9: F | C9: 2 | D9: 2 | E9: 0 | F9: 2 | G9: 保留双方原值；未取得逐维共同裁定
A10: CAL-07 | B10: E | C10: 2 | D10: 2 | E10: 0 | F10: 2 | G10: 保留双方原值；未取得逐维共同裁定
A11: CAL-07 | B11: C | C11: 2 | D11: 2 | E11: 1 | F11: 0 | G11: 保留双方原值；未取得逐维共同裁定

Sheet 11_D评分原值
A1: 匿名ID | B1: 题号 | C1: F | D1: E | E1: C | F1: B | G1: 关键错误 | H1: U | I1: 无依据 | J1: 过度拒答 | K1: 覆盖 | L1: 应覆盖 | M1: 通过 | N1: 理由
A2: CAL-01 | B2: P-A07 | C2: 2 | D2: 2 | E2: 2 | F2: 2 | G2: =FALSE() -> FALSE | H2: =FALSE() -> FALSE | I2: =FALSE() -> FALSE | J2: =FALSE() -> FALSE | K2: 3 | L2: 3 | M2: =TRUE() -> TRUE | N2: F:2.09%、4.76亿(4.759亿舍入)、研发费用+1.33%均与SP_AR_p016一致。E:p016引用支持全部事实。C:覆盖投入规模/趋势、研发方向(消费者需求导向/差异化/安全环保便捷)，并正确拒答同行对比与竞争力影响(证据确实未披露)，3/3核心完成。B:明确区分事实与未知，无编造。非过度拒答：可答事实已答，未知部分如实说明并建议关注后续公告。 【口径G05】"+1.33%"为研发投入金额同比（p016：475,923,455.10元对469,662,999.96元），与占比同比0.00%分属两个口径；"4.76亿"按R02半个显示单位容差（±0.005亿）覆盖4.759亿，舍入成立。
A3: CAL-02 | B3: P-A08 | C3: 2 | D3: 2 | E3: 1 | F3: 2 | G3: =FALSE() -> FALSE | H3: =FALSE() -> FALSE | I3: =FALSE() -> FALSE | J3: =FALSE() -> FALSE | K3: 2 | L3: 3 | M3: =FALSE() -> FALSE | N3: F:炊具销量92,664,612/+8.10%、炊具收入69.66亿/+1.89%、总营收227.72亿/+1.54%、外销74.38亿/-0.85%均与p012/p013/p014一致。E:引用页码支持。C:完成(1)量收事实与(3)边界(单价无法确认/外销拖累)，但缺(2)类别均价近似计算(约79.75→75.17元/台、约-5.74%)，仅定性'与单价下降方向一致'，核心计算未完成，C=1。B:正确标注'无法确认降价幅度及是否为唯一原因'，外销作背景提及非必答。 【口径G01/G02】覆盖2/3，按一一对应映射计C=1；合格要求C=2，故不影响不合格结论。缺项为类别均价近似测算（约79.75→75.17元/台、约-5.74%）。
A4: CAL-03 | B4: P-A07 | C4: 2 | D4: 2 | E4: 2 | F4: 2 | G4: =FALSE() -> FALSE | H4: =FALSE() -> FALSE | I4: =FALSE() -> FALSE | J4: =FALSE() -> FALSE | K4: 3 | L4: 3 | M4: =TRUE() -> TRUE | N4: F:4.759亿、2.09%、与2024持平、全部费用化无资本化、研发人员1,387人占12.91%均与p016一致。E:p016引用到位。C:覆盖投入规模/结构(资本化、人员)、研发方向(差异化厨房产品/拓展品类/提升附加值)、边界处理(同行差异原因证据未解释、无法判断竞争力)，3/3完成。B:明确'信息缺口'，无编造。 【口径G05】"与2024年持平"紧邻"占营业收入2.09%"，按就近原则判为占比持平（p016：2.09%对2.09%、变动0.00%），与金额同比+1.33%不冲突，F=2。
A5: CAL-04 | B5: P-A08 | C5: 2 | D5: 2 | E5: 0 | F5: 1 | G5: =TRUE() -> TRUE | H5: =FALSE() -> FALSE | I5: =TRUE() -> TRUE | J5: =FALSE() -> FALSE | K5: 1 | L5: 3 | M5: =FALSE() -> FALSE | N5: F:销量+8.10%、炊具收入+1.89%、营业成本+2.17%、毛利率-0.20pp、食物料理-1.64%(p12)、外销SEB需求减少均与p012/p013/p014一致，数字本身无错。E:引用页码正确。关键错误=是：将'营收仅增1.89%主要因营业成本增速(2.17%)高于营收增速导致毛利率微降'当作量增收平的主因——混淆了营收与毛利：成本增速影响利润表毛利，不解释销量+8.10%与营收+1.89%之间的量价缺口；该错误改变核心判断(把成本/毛利问题当作单价问题的答案)。C:缺类别均价计算，因果链错误，C=1。B:以'量价与成本综合结果'作结但因果表述错误，B=1。无依据回答=是。 【口径G01/G02】覆盖1/3，按一一对应映射计C=0（上一版误计C=1，本次更正）；本条已因关键错误一票否决，C分更正不改变不合格结论。
A6: CAL-05 | B6: P-A08 | C6: 2 | D6: 2 | E6: 0 | F6: 2 | G6: =FALSE() -> FALSE | H6: =FALSE() -> FALSE | I6: =FALSE() -> FALSE | J6: =TRUE() -> TRUE | K6: 1 | L6: 3 | M6: =FALSE() -> FALSE | N6: F:销量+8.10%、炊具收入69.66亿/+1.89%、毛利率-0.20pp均与p012/p013/p014一致。E:引用到位。C:完成(1)量收事实，但缺(2)类别均价近似计算，并以'年报未披露分产品平均售价'为由回避可由收入/销量近似计算的单价方向；'并未出现停滞不前'未分析量价差距即否定提问前提。C=1。B:对未知('无法直接确认是否单价下降')标注正确，'持续优化产品结构/提升品牌溢价'为泛化表述非事实断言，B=2。过度拒答=是：回避了可由p012收入+p014销量近似计算的单价方向(约-5.74%)。 【口径G04】"公司将持续优化产品结构，提升品牌溢价能力"为收尾泛化陈述，未被用于填补"是否单价下降导致"这一核心未知，故B=2；与CAL-07将无依据断言直接用于回答核心未知（B=0）相区分，判分差异源于G04口径。【口径G01/G02】覆盖1/3，按一一对应映射计C=0（上一版误计C=1，本次更正）。
A7: CAL-06 | B7: P-A07 | C7: 2 | D7: 2 | E7: 2 | F7: 2 | G7: =FALSE() -> FALSE | H7: =FALSE() -> FALSE | I7: =FALSE() -> FALSE | J7: =FALSE() -> FALSE | K7: 3 | L7: 3 | M7: =TRUE() -> TRUE | N7: F:研发投入475,923,455.10元、占营收2.09%、与上年持平、研发人员1,387人占12.91%均与p016一致。E:p016引用到位。C:覆盖投入规模(精确金额)/趋势/人员/方向，并正确处理三项边界：同行3%+前提'证据未提供可比公司数据无法核实'、低投入原因'年报未说明'、竞争力影响'属前瞻判断缺乏证据暂无法回答，3/3完成。B:边界处理清晰，无编造。 【口径G05】"与上年持平"紧邻"占营业收入2.09%"，按就近原则判为占比持平（p016变动0.00%），与金额同比+1.33%不冲突，F=2。
A8: CAL-07 | B8: P-A07 | C8: 2 | D8: 2 | E8: 0 | F8: 0 | G8: =TRUE() -> TRUE | H8: =FALSE() -> FALSE | I8: =TRUE() -> TRUE | J8: =FALSE() -> FALSE | K8: 1 | L8: 3 | M8: =FALSE() -> FALSE | N8: F:研发费用占营收2.09%、资本化率0%与p016一致。E:p016引用到位。关键错误=是：①接受'同行比例较高'为已证事实(证据未提供同行数据，提问前提不可采信)；②'凭借对用户体验的极致关注及成熟的供应链体系保持了竞争优势''低占比是商业模式差异所致''旨在平衡创新效率与股东回报''未损害长期竞争力'均为无依据断言，p016无此表述——直接对'是否损害竞争力'给出肯定结论。B=0(添加关键无依据断言、采信提问前提)。C:仅完成占比与研发方向，未知部分被编造填充，C=1。无依据回答=是。 【口径G06】E=2仅指事实性数字（研发费用占营收2.09%、资本化率0%）引用到位；[SP_AR_p016]被延伸至"通过精准投入提升附加值""保持了竞争优势"等p016不支持的表述，该部分按B=0与关键错误=是记录，不在E重复扣分（v0.10第1条）。【口径G01/G02】覆盖1/3，按一一对应映射计C=0（上一版误计C=1，本次更正）。
A9: CAL-08 | B9: P-A08 | C9: 2 | D9: 2 | E9: 1 | F9: 2 | G9: =FALSE() -> FALSE | H9: =FALSE() -> FALSE | I9: =FALSE() -> FALSE | J9: =FALSE() -> FALSE | K9: 2 | L9: 3 | M9: =FALSE() -> FALSE | N9: F:销量+8.10%、炊具营收+1.89%、外销-0.85%、SEB外销客户需求略减、食物料理电器-1.64%(p12)均与p012/p013/p014一致。E:引用页码支持。C:完成(1)量收事实、(3)边界(外销/食物料理作背景、'非单一因素')，但缺(2)类别均价近似计算的具体数值(约79.75→75.17、约-5.74%)，仅定性'单价确有下行压力'并标注'无法量化降幅'，核心计算未完成，C=1。B:明确区分推断('下行压力')与事实，标注量化缺口。 【口径G01/G02】覆盖2/3，按一一对应映射计C=1；合格要求C=2，故不影响不合格结论。缺项为类别均价近似测算的具体数值（约79.75→75.17元/台、约-5.74%）。

Sheet 12_规则差异
A1: 对象 | B1: D口径 | C1: 核对意见 | D1: 处理
A2: G01/G02 | B2: 3/3→2，2/3→1，1/3→0，0/3无档位 | C2: v11既有规则：完整=2，部分=1，无可答核心完成=0；1/3与2/3均属部分 | D2: 保留D原分；若统一须映射1/3→1、0/3→0，不发明负分。当前合格名单不变。
A3: G03 | B3: P-A07另把研发方向设为一组核心 | C3: 与A三组（自身数据/同行前提/竞争边界）不同 | D3: 覆盖计数含义不同，不把相同分母3当相同指标；本批门槛一致不证明定义一致。
A4: G06 | B4: 引用覆盖数字即E=2，无依据评价只扣B | C4: E应检验关键陈述是否被支持，不仅检查数字；维度不加总，不需要防止同一问题影响多维 | D4: 保留D的E=2与助手E=0并列，未取得细项共识。
A5: G04及CAL04 | B5: 错误因果但留部分边界意识→B=1 | C5: 助手将关键无依据因果确定化→B=0 | D5: 两者均关键错误=是，不影响不合格；严重程度不同。
A6: CAL05 | B6: 过度拒答=是，覆盖1/3；泛化收尾不计事实 | C6: A辅助沿用否、覆盖2/3；收尾需按内容核查 | D6: 暂并列，不声称已经统一过度拒答率；标注口径范围0/8至1/8，非置信区间。
A7: R01—05/E01—07 | B7: 新07/08表全部填同意；旧04表仍保留原意见 | C7: 按新回复登记D已接受建议；不把旧意见当最终同意，也不称正式事前冻结 | D7: 保留历史，继续修正规则。
A8: 敏感性结论 | B8: D说均值核心被否只会单向下修 | C8: 改变核心定义可能双向影响，不能据主观概率宣称只会下修 | D8: 保留原话作意见；报告不采用这一未经验证的方向断言。

Sheet 13_合格成本与一致率
A1: 指标 | B1: 数值或公式 | C1: 口径
A2: 输出数 | B2: 8 | C2: 只有两道独立问题
A3: 首次A通过数 | B3: 8 | C3: 原评分留存
A4: D通过数 | B4: 3 | C4: D两份文件一致
A5: 首次A与D一致数 | B5: 3 | C5: 仅CAL01、03、06
A6: 首次门槛一致率 | B6: =B5/B2 -> 0.375 | C6: 描述性；不同细则
A7: 机会一致率 | B7: =(B3/B2)*(B4/B2)+(1-B3/B2)*(1-B4/B2) -> 0.375 | C7: A首次全部同类
A8: 描述性kappa | B8: =(B6-B7)/(1-B7) -> 0 | C8: 非正式共同规则信度检验
A9: API参考费用合计 | B9: ='01_逐次费用'!I10 -> 0.0155928 | C9: 元，非实付
A10: 当前共同门槛合格数 | B10: =COUNTIF('03_A校准与D门槛'!L2:L9,"通过") -> 3 | C10: A校准后与D共同通过；未统一细项
A11: 合格草稿单位API参考成本 | B11: =IF(B10>0,B9/B10,"未定义") -> 0.0051976 | C11: 仅本批；不含准备、人工和部署
A12: 平均生成API参考费用 | B12: =B9/B2 -> 0.0019491 | C12: 元/次
A13: 两单位成本之比 | B13: =B11/B12 -> 2.6666667 | C13: 分母改变，非模型改善
A14: 校准后门槛一致数 | B14: 8 | C14: 非首次独立一致
A15: D过度拒答标记数 | B15: 1 | C15: CAL05
A16: A辅助视图过度拒答标记数 | B16: 0 | C16: 两口径并列，非置信区间
