Workbook

Sheet 00_口径说明
A1: 项目 | B1: 说明
A2: 数据截点 | B2: 2026-10-28；尚未收到D独立输出评分，未完成受控人工写作任务。
A3: 用途 | B3: 本簿区分日志实测、参考费用、评分校准和假设情景。不能把情景工资/时间写成企业实测。
A4: 身份 | B4: 金金有味队：李牧轩、刘铠侨、李泽锴、黄玺诺；天津大学分赛场。
A5: 费用 | B5: 每次(input_tokens×input_rate+output_tokens×output_rate)/1000000；本轮缓存命中0。
A6: 评价 | B6: 当前3/8只是A复核及助手辅助视图；无D双评、无最终合格成本。
A7: 来源 | B7: 01日志来自C交付经核验数据；评分来自v1.5。参考链接见文稿。
A8: 公式 | B8: Excel公式可重算；绿色或蓝色值为已记录数据，情景假设另表。空白实付、D评分均不得填0。
A9: 保密流程 | B9: D独立提交前不要看本表模型映射、A分数和辅助裁定；公开仓库不是权限隔离。

Sheet 01_逐次费用
A1: 匿名ID | B1: 题号 | C1: 模型 | D1: 流程 | E1: 输入Token | F1: 输出Token | G1: 输入单价_元每百万 | H1: 输出单价_元每百万 | I1: 复算费用_元 | J1: 原记录参考费_元 | K1: 差额 | L1: 缓存命中Token | M1: 调用时间北京时间 | N1: 实际支付_待账单 | O1: 来源状态
A2: CAL-01 | B2: P-A07 | C2: 千问 | D2: boundary | E2: 1339 | F2: 276 | G2: 0.2 | H2: 0.8 | I2: =(E2*G2+F2*H2)/1000000 -> 0.0004886 | J2: 0.0004886 | K2: =I2-J2 -> 0 | L2: 0 | M2: 2026-10-24T00:08:04.880+08:00 | O2: 日志用量；单价复算，非实付
A3: CAL-02 | B3: P-A08 | C3: DeepSeek | D3: boundary | E3: 3737 | F3: 229 | G3: 1 | H3: 4 | I3: =(E3*G3+F3*H3)/1000000 -> 0.004653 | J3: 0.004653 | K3: =I3-J3 -> 0 | L3: 0 | M3: 2026-10-24T00:08:09.272+08:00 | O3: 日志用量；单价复算，非实付
A4: CAL-03 | B4: P-A07 | C4: DeepSeek | D4: direct | E4: 1104 | F4: 123 | G4: 1 | H4: 4 | I4: =(E4*G4+F4*H4)/1000000 -> 0.001596 | J4: 0.001596 | K4: =I4-J4 -> 0 | L4: 0 | M4: 2026-10-24T00:08:12.227+08:00 | O4: 日志用量；单价复算，非实付
A5: CAL-04 | B5: P-A08 | C5: 千问 | D5: direct | E5: 4530 | F5: 192 | G5: 0.2 | H5: 0.8 | I5: =(E5*G5+F5*H5)/1000000 -> 0.0010596 | J5: 0.0010596 | K5: =I5-J5 -> 0 | L5: 0 | M5: 2026-10-24T00:08:13.997+08:00 | O5: 日志用量；单价复算，非实付
A6: CAL-05 | B6: P-A08 | C6: 千问 | D6: boundary | E6: 4577 | F6: 296 | G6: 0.2 | H6: 0.8 | I6: =(E6*G6+F6*H6)/1000000 -> 0.0011522 | J6: 0.0011522 | K6: =I6-J6 -> 0 | L6: 0 | M6: 2026-10-24T00:08:18.342+08:00 | O6: 日志用量；单价复算，非实付
A7: CAL-06 | B7: P-A07 | C7: DeepSeek | D7: boundary | E7: 1152 | F7: 207 | G7: 1 | H7: 4 | I7: =(E7*G7+F7*H7)/1000000 -> 0.00198 | J7: 0.00198 | K7: =I7-J7 -> 0 | L7: 0 | M7: 2026-10-24T00:08:25.046+08:00 | O7: 日志用量；单价复算，非实付
A8: CAL-07 | B8: P-A07 | C8: 千问 | D8: direct | E8: 1292 | F8: 145 | G8: 0.2 | H8: 0.8 | I8: =(E8*G8+F8*H8)/1000000 -> 0.0003744 | J8: 0.0003744 | K8: =I8-J8 -> 0 | L8: 0 | M8: 2026-10-24T00:08:27.584+08:00 | O8: 日志用量；单价复算，非实付
A9: CAL-08 | B9: P-A08 | C9: DeepSeek | D9: direct | E9: 3689 | F9: 150 | G9: 1 | H9: 4 | I9: =(E9*G9+F9*H9)/1000000 -> 0.004289 | J9: 0.004289 | K9: =I9-J9 -> 0 | L9: 0 | M9: 2026-10-24T00:08:31.304+08:00 | O9: 日志用量；单价复算，非实付
A10: 合计 | E10: =SUM(E2:E9) -> 21420 | F10: =SUM(F2:F9) -> 1618 | I10: =SUM(I2:I9) -> 0.0155928 | J10: =SUM(J2:J9) -> 0.0155928 | K10: =SUM(K2:K9) -> 0 | L10: =SUM(L2:L9) -> 0 | O10: 8次/2题

Sheet 02_四条件汇总
A1: 模型 | B1: 流程 | C1: 次数 | D1: 输入Token | E1: 输出Token | F1: 参考费用合计 | G1: 平均每次费用 | H1: 备注
A2: DeepSeek | B2: direct | C2: =COUNTIFS('01_逐次费用'!$C$2:$C$9,A2,'01_逐次费用'!$D$2:$D$9,B2) -> 2 | D2: =SUMIFS('01_逐次费用'!$E$2:$E$9,'01_逐次费用'!$C$2:$C$9,A2,'01_逐次费用'!$D$2:$D$9,B2) -> 4793 | E2: =SUMIFS('01_逐次费用'!$F$2:$F$9,'01_逐次费用'!$C$2:$C$9,A2,'01_逐次费用'!$D$2:$D$9,B2) -> 273 | F2: =SUMIFS('01_逐次费用'!$I$2:$I$9,'01_逐次费用'!$C$2:$C$9,A2,'01_逐次费用'!$D$2:$D$9,B2) -> 0.005885 | G2: =F2/C2 -> 0.0029425 | H2: 两题各一次，不做质量排名
A3: DeepSeek | B3: boundary | C3: =COUNTIFS('01_逐次费用'!$C$2:$C$9,A3,'01_逐次费用'!$D$2:$D$9,B3) -> 2 | D3: =SUMIFS('01_逐次费用'!$E$2:$E$9,'01_逐次费用'!$C$2:$C$9,A3,'01_逐次费用'!$D$2:$D$9,B3) -> 4889 | E3: =SUMIFS('01_逐次费用'!$F$2:$F$9,'01_逐次费用'!$C$2:$C$9,A3,'01_逐次费用'!$D$2:$D$9,B3) -> 436 | F3: =SUMIFS('01_逐次费用'!$I$2:$I$9,'01_逐次费用'!$C$2:$C$9,A3,'01_逐次费用'!$D$2:$D$9,B3) -> 0.006633 | G3: =F3/C3 -> 0.0033165 | H3: 两题各一次，不做质量排名
A4: 千问 | B4: direct | C4: =COUNTIFS('01_逐次费用'!$C$2:$C$9,A4,'01_逐次费用'!$D$2:$D$9,B4) -> 2 | D4: =SUMIFS('01_逐次费用'!$E$2:$E$9,'01_逐次费用'!$C$2:$C$9,A4,'01_逐次费用'!$D$2:$D$9,B4) -> 5822 | E4: =SUMIFS('01_逐次费用'!$F$2:$F$9,'01_逐次费用'!$C$2:$C$9,A4,'01_逐次费用'!$D$2:$D$9,B4) -> 337 | F4: =SUMIFS('01_逐次费用'!$I$2:$I$9,'01_逐次费用'!$C$2:$C$9,A4,'01_逐次费用'!$D$2:$D$9,B4) -> 0.001434 | G4: =F4/C4 -> 0.000717 | H4: 两题各一次，不做质量排名
A5: 千问 | B5: boundary | C5: =COUNTIFS('01_逐次费用'!$C$2:$C$9,A5,'01_逐次费用'!$D$2:$D$9,B5) -> 2 | D5: =SUMIFS('01_逐次费用'!$E$2:$E$9,'01_逐次费用'!$C$2:$C$9,A5,'01_逐次费用'!$D$2:$D$9,B5) -> 5916 | E5: =SUMIFS('01_逐次费用'!$F$2:$F$9,'01_逐次费用'!$C$2:$C$9,A5,'01_逐次费用'!$D$2:$D$9,B5) -> 572 | F5: =SUMIFS('01_逐次费用'!$I$2:$I$9,'01_逐次费用'!$C$2:$C$9,A5,'01_逐次费用'!$D$2:$D$9,B5) -> 0.0016408 | G5: =F5/C5 -> 0.0008204 | H5: 两题各一次，不做质量排名

Sheet 03_校准记录非双评
A1: 匿名ID | B1: 题号 | C1: F | D1: E | E1: C | F1: B | G1: 关键错误 | H1: 标准U | I1: 当前门槛 | J1: 评分来源 | K1: D评分_空白 | L1: 最终裁定_空白
A2: CAL-01 | B2: P-A07 | C2: 2 | D2: 2 | E2: 2 | F2: 2 | G2: 否 | H2: 否 | I2: 通过 | J2: 沿用A复核版
A3: CAL-02 | B3: P-A08 | C3: 2 | D3: 2 | E3: 1 | F3: 2 | G3: 否 | H3: 否 | I3: 未通过 | J3: 沿用A复核版
A4: CAL-03 | B4: P-A07 | C4: 2 | D4: 2 | E4: 2 | F4: 2 | G4: 否 | H4: 否 | I4: 通过 | J4: 沿用A复核版
A5: CAL-04 | B5: P-A08 | C5: 0 | D5: 0 | E5: 1 | F5: 0 | G5: 是 | H5: 否 | I5: 未通过 | J5: 助手辅助裁定
A6: CAL-05 | B6: P-A08 | C6: 2 | D6: 2 | E6: 1 | F6: 2 | G6: 否 | H6: 否 | I6: 未通过 | J6: 沿用A复核版
A7: CAL-06 | B7: P-A07 | C7: 2 | D7: 2 | E7: 2 | F7: 2 | G7: 否 | H7: 否 | I7: 通过 | J7: 沿用A复核版
A8: CAL-07 | B8: P-A07 | C8: 0 | D8: 0 | E8: 1 | F8: 0 | G8: 是 | H8: 否 | I8: 未通过 | J8: 助手辅助裁定
A9: CAL-08 | B9: P-A08 | C9: 2 | D9: 2 | E9: 1 | F9: 2 | G9: 否 | H9: 否 | I9: 未通过 | J9: 沿用A复核版

Sheet 04_价格折扣情景
A1: 假设API成本占比 | B1: 假设API降价比例 | C1: 总成本下降比例 | D1: 其他条件
A2: 0 | B2: 0.5 | C2: =A2*B2 -> 0 | D2: 质量/用量/人工/合格数固定；非实测占比
A3: 0.01 | B3: 0.5 | C3: =A3*B3 -> 0.005 | D3: 质量/用量/人工/合格数固定；非实测占比
A4: 0.05 | B4: 0.5 | C4: =A4*B4 -> 0.025 | D4: 质量/用量/人工/合格数固定；非实测占比
A5: 0.1 | B5: 0.5 | C5: =A5*B5 -> 0.05 | D5: 质量/用量/人工/合格数固定；非实测占比
A6: 0.2 | B6: 0.5 | C6: =A6*B6 -> 0.1 | D6: 质量/用量/人工/合格数固定；非实测占比
A7: 0.3 | B7: 0.5 | C7: =A7*B7 -> 0.15 | D7: 质量/用量/人工/合格数固定；非实测占比
A8: 0.5 | B8: 0.5 | C8: =A8*B8 -> 0.25 | D8: 质量/用量/人工/合格数固定；非实测占比
A9: 0.75 | B9: 0.5 | C9: =A9*B9 -> 0.375 | D9: 质量/用量/人工/合格数固定；非实测占比
A10: 1 | B10: 0.5 | C10: =A10*B10 -> 0.5 | D10: 质量/用量/人工/合格数固定；非实测占比

Sheet 05_人工时间情景
A1: 假设小时价值 | B1: 假设分钟每条 | C1: 平均API费锚点 | D1: 人工费用 | E1: 部分总额 | F1: API降价50%后部分总额 | G1: 总额降幅 | H1: 说明
A2: 60 | B2: 0 | C2: ='01_逐次费用'!I10/8 -> 0.0019491 | D2: =A2*B2/60 -> 0 | E2: =C2+D2 -> 0.0019491 | F2: =C2*0.5+D2 -> 0.00097455 | G2: =(E2-F2)/E2 -> 0.5 | H2: 情景；未计准备、部署及质量差异
A3: 60 | B3: 1 | C3: ='01_逐次费用'!I10/8 -> 0.0019491 | D3: =A3*B3/60 -> 1 | E3: =C3+D3 -> 1.0019491 | F3: =C3*0.5+D3 -> 1.0009746 | G3: =(E3-F3)/E3 -> 0.0009726542 | H3: 情景；未计准备、部署及质量差异
A4: 60 | B4: 3 | C4: ='01_逐次费用'!I10/8 -> 0.0019491 | D4: =A4*B4/60 -> 3 | E4: =C4+D4 -> 3.0019491 | F4: =C4*0.5+D4 -> 3.0009746 | G4: =(E4-F4)/E4 -> 0.00032463908 | H4: 情景；未计准备、部署及质量差异
A5: 60 | B5: 5 | C5: ='01_逐次费用'!I10/8 -> 0.0019491 | D5: =A5*B5/60 -> 5 | E5: =C5+D5 -> 5.0019491 | F5: =C5*0.5+D5 -> 5.0009745 | G5: =(E5-F5)/E5 -> 0.00019483405 | H5: 情景；未计准备、部署及质量差异
A6: 60 | B6: 10 | C6: ='01_逐次费用'!I10/8 -> 0.0019491 | D6: =A6*B6/60 -> 10 | E6: =C6+D6 -> 10.001949 | F6: =C6*0.5+D6 -> 10.000975 | G6: =(E6-F6)/E6 -> 9.7436009e-05 | H6: 情景；未计准备、部署及质量差异
A7: 120 | B7: 0 | C7: ='01_逐次费用'!I10/8 -> 0.0019491 | D7: =A7*B7/60 -> 0 | E7: =C7+D7 -> 0.0019491 | F7: =C7*0.5+D7 -> 0.00097455 | G7: =(E7-F7)/E7 -> 0.5 | H7: 情景；未计准备、部署及质量差异
A8: 120 | B8: 1 | C8: ='01_逐次费用'!I10/8 -> 0.0019491 | D8: =A8*B8/60 -> 2 | E8: =C8+D8 -> 2.0019491 | F8: =C8*0.5+D8 -> 2.0009746 | G8: =(E8-F8)/E8 -> 0.00048680059 | H8: 情景；未计准备、部署及质量差异
A9: 120 | B9: 3 | C9: ='01_逐次费用'!I10/8 -> 0.0019491 | D9: =A9*B9/60 -> 6 | E9: =C9+D9 -> 6.0019491 | F9: =C9*0.5+D9 -> 6.0009745 | G9: =(E9-F9)/E9 -> 0.00016237225 | H9: 情景；未计准备、部署及质量差异
A10: 120 | B10: 5 | C10: ='01_逐次费用'!I10/8 -> 0.0019491 | D10: =A10*B10/60 -> 10 | E10: =C10+D10 -> 10.001949 | F10: =C10*0.5+D10 -> 10.000975 | G10: =(E10-F10)/E10 -> 9.7436009e-05 | H10: 情景；未计准备、部署及质量差异
A11: 120 | B11: 10 | C11: ='01_逐次费用'!I10/8 -> 0.0019491 | D11: =A11*B11/60 -> 20 | E11: =C11+D11 -> 20.001949 | F11: =C11*0.5+D11 -> 20.000975 | G11: =(E11-F11)/E11 -> 4.8722752e-05 | H11: 情景；未计准备、部署及质量差异
A12: 240 | B12: 0 | C12: ='01_逐次费用'!I10/8 -> 0.0019491 | D12: =A12*B12/60 -> 0 | E12: =C12+D12 -> 0.0019491 | F12: =C12*0.5+D12 -> 0.00097455 | G12: =(E12-F12)/E12 -> 0.5 | H12: 情景；未计准备、部署及质量差异
A13: 240 | B13: 1 | C13: ='01_逐次费用'!I10/8 -> 0.0019491 | D13: =A13*B13/60 -> 4 | E13: =C13+D13 -> 4.0019491 | F13: =C13*0.5+D13 -> 4.0009745 | G13: =(E13-F13)/E13 -> 0.00024351884 | H13: 情景；未计准备、部署及质量差异
A14: 240 | B14: 3 | C14: ='01_逐次费用'!I10/8 -> 0.0019491 | D14: =A14*B14/60 -> 12 | E14: =C14+D14 -> 12.001949 | F14: =C14*0.5+D14 -> 12.000975 | G14: =(E14-F14)/E14 -> 8.1199311e-05 | H14: 情景；未计准备、部署及质量差异
A15: 240 | B15: 5 | C15: ='01_逐次费用'!I10/8 -> 0.0019491 | D15: =A15*B15/60 -> 20 | E15: =C15+D15 -> 20.001949 | F15: =C15*0.5+D15 -> 20.000975 | G15: =(E15-F15)/E15 -> 4.8722752e-05 | H15: 情景；未计准备、部署及质量差异
A16: 240 | B16: 10 | C16: ='01_逐次费用'!I10/8 -> 0.0019491 | D16: =A16*B16/60 -> 40 | E16: =C16+D16 -> 40.001949 | F16: =C16*0.5+D16 -> 40.000975 | G16: =(E16-F16)/E16 -> 2.4362563e-05 | H16: 情景；未计准备、部署及质量差异

Sheet 06_炊具均值复算
A1: 期间 | B1: 收入元 | C1: 销量台或套 | D1: 类别平均收入 | E1: 平均收入同比 | F1: 证据
A2: 2024 | B2: 6.836158e+09 | C2: 85724597 | D2: =B2/C2 -> 79.745584 | F2: 苏泊尔年报原13—14页
A3: 2025 | B3: 6.965678e+09 | C3: 92664612 | D3: =B3/C3 -> 75.170854 | E3: =D3/D2-1 -> -0.057366565 | F3: 推导值，不是同款价格

Sheet 07_文献与页码
A1: 编号 | B1: 文献 | C1: 类型 | D1: 样本 | E1: 指标 | F1: 结论边界 | G1: 正文页码 | H1: PDF对应 | I1: 链接
A2: 3 | B2: Chen等，2025-08-05 | C2: 工作稿，非期刊 | D2: 4680公司；7818963公司—交易日 | E2: 报价价差；提问/评论及回复分类 | F2: 质量关联不能当AI生成准确率或因果 | G2: 9—10；18—21；表6B 45 | H2: 正文+1 | I2: https://papers.ssrn.com/sol3/papers.cfm?abstract_id=4281898
A3: 4 | B3: 徐寿福、郑迎飞、罗雨杰，2022 | C3: 财经研究48(10):153—168 | D3: 92155公司—季度 | E3: 互动频次/文本；残差波动 | F3: 互动与风险关系不证明AI造成风险 | G3: 156—159；162 | H3: 印刷页-152 | I3: https://qks.shufe.edu.cn/j/PDFFull/17794c14-b22d-4e71-b91b-053fc480a45a.pdf
A4: 5 | B4: 樊犇、吴燕博、刘恒源，2026 | C4: 审计与经济研究41(4):94—104 | D4: 25996公司—年度 | E4: LLM识别监督；真实盈余管理 | F4: LLM文本测量不等于生成回复可靠 | G4: 97—101 | H4: 印刷页-93 | I4: https://xbbjb.nau.edu.cn/sjyjjyj/article/abstract/20260204010

Sheet 08_提交检查
A1: 事项 | B1: 当前状态 | C1: 操作 | D1: 依据
A2: 赛场 | B2: 已确认 | C2: 仅天津大学分赛场 | D2: 用户10/28确认；手册16—18页
A3: 截止 | B3: 已确认 | C3: 2026-10-29 22:00前，内部18:00 | D3: 用户确认天大通知有效
A4: 邮箱 | B4: 已确认 | C4: tjucomers2026@163.com；发送Word和PDF | D4: 用户确认；助手未代发
A5: 署名 | B5: 已确认 | C5: 金金有味队；李牧轩 刘铠侨 李泽锴 黄玺诺 | D5: 用户提供
A6: 电话邮箱 | B6: 不在公开稿中收集 | C6: 队长本地补入正式提交文件名 | D6: 手册命名格式及本地通知
A7: 全文字数 | B7: 程序检查后记录 | C7: 全文含附录、参考文献、文本框、脚注尾注均控制30000以内 | D7: 手册18页
A8: 字体 | B8: Word已设；PDF环境替代 | C8: 有宋体/Times New Roman电脑本地打开Word重新导出PDF | D8: 当前环境缺规定字体
A9: D评分 | B9: 未回收 | C9: 收到后保留独立版，更新第3.5/4.4及摘要附录 | D9: 现有仅单人和助手辅助
A10: C账单 | B10: 未回收 | C10: 实付缺失则保留参考价标签，不填0 | D10: 费用来源
A11: 新增样本 | B11: 待核验 | C11: 合格来源补入收集状态；无新调用不能增加实验数 | D11: 时间截止原则
A12: 附件一致 | B12: 待最终本地导出 | C12: 打开Word/PDF逐页检查图表、字体、目录及页码 | D12: 提交前
A13: 发送回执 | B13: 未发送 | C13: 核对邮箱/文件名/附件可读，保存发送及回执 | D13: 队长执行
